rsize/__init__.py
rsize/command.py
rsize/formatter.py
rsize/google_spreadsheets.py
rsize/pkg_util.py
rsize-0.1.9.dist-info/METADATA
rsize-0.1.9.dist-info/WHEEL
rsize-0.1.9.dist-info/entry_points.txt
rsize-0.1.9.dist-info/RECORD
